onaws/__init__.py
onaws/__main__.py
onaws/cli.py
onaws/core.py
onaws/ipranges.py
onaws-1.0.3.dist-info/LICENSE
onaws-1.0.3.dist-info/METADATA
onaws-1.0.3.dist-info/WHEEL
onaws-1.0.3.dist-info/entry_points.txt
onaws-1.0.3.dist-info/top_level.txt
onaws-1.0.3.dist-info/RECORD
