Metadata-Version: 2.1
Name: onaws
Version: 1.0.3
Summary: Library to fetch the details of assets hosted on AWS.
Home-page: https://github.com/amalmurali47/onaws
Author: Amal Murali
Author-email: amalmurali47@gmail.com
License: UNKNOWN
Platform: UNKNOWN
Classifier: Programming Language :: Python :: 3
Classifier: License :: OSI Approved :: MIT License
Classifier: Operating System :: OS Independent
Requires-Python: >=3.6
License-File: LICENSE
Requires-Dist: requests (>=2.25.1)
Requires-Dist: pytricia (>=1.0.2)
